Workbook

Sheet Início
B2: FORNECEDORVIP
B3: Planilha de Controle + Precificação
B4: Sua revenda organizada e lucrativa, sem precisar entender de planilha.
B7: COMO USAR (leva 2 minutos):
B8: As células em amarelo são as únicas que você preenche. O resto a planilha calcula sozinha.
B10: 1) Aba PRECIFICAÇÃO
B11: Coloque o custo do produto, o frete e a taxa do marketplace. A planilha te diz o preço de venda ideal e o lucro de cada produto. Nunca mais venda no prejuízo.
B13: 2) Aba CONTROLE DE VENDAS
B14: Anote cada venda. A planilha calcula faturamento, taxas e lucro automaticamente.
B16: 3) Aba CONTROLE DE ESTOQUE
B17: Acompanhe quanto você tem de cada produto. Ela avisa quando é hora de repor.
B19: 4) Aba RESUMO
... B22: DICA: comece pela aba Precificação para nunca errar o preço. É lá que está o lucro.

Sheet Precificação
A1: PRECIFICAÇÃO INTELIGENTE — preencha as colunas amarelas e veja o preço ideal
A2: Produto | B2: Custo do produto (R$) | C2: Frete + embalagem (R$) | D2: Taxa do marketplace (%) | E2: Margem de lucro desejada (%) | F2: Custo total (R$) | G2: PREÇO DE VENDA ideal (R$) | H2: Lucro por venda (R$) | I2: Margem real (%)
A3: Conjunto fitness | B3: 22 | C3: 8 | D3: 0.2 | E3: 0.3 | F3: =IF(B3="","",B3+C3) | G3: =IFERROR(IF(F3="","",F3/(1-D3-E3)),"rever %") | H3: =IFERROR(IF(G3="","",G3-F3-G3*D3),"") | I3: =IFERROR(IF(G3="","",H3/G3),"")
A4: Perfume importado 50ml | B4: 35 | C4: 6 | D4: 0.16 | E4: 0.35 | F4: =IF(B4="","",B4+C4) | G4: =IFERROR(IF(F4="","",F4/(1-D4-E4)),"rever %") | H4: =IFERROR(IF(G4="","",G4-F4-G4*D4),"") | I4: =IFERROR(IF(G4="","",H4/G4),"")
A5: Kit maquiagem | B5: 28 | C5: 7 | D5: 0.2 | E5: 0.3 | F5: =IF(B5="","",B5+C5) | G5: =IFERROR(IF(F5="","",F5/(1-D5-E5)),"rever %") | H5: =IFERROR(IF(G5="","",G5-F5-G5*D5),"") | I5: =IFERROR(IF(G5="","",H5/G5),"")
F6: =IF(B6="","",B6+C6) | G6: =IFERROR(IF(F6="","",F6/(1-D6-E6)),"rever %") | H6: =IFERROR(IF(G6="","",G6-F6-G6*D6),"") | I6: =IFERROR(IF(G6="","",H6/G6),"")
F7: =IF(B7="","",B7+C7) | G7: =IFERROR(IF(F7="","",F7/(1-D7-E7)),"rever %") | H7: =IFERROR(IF(G7="","",G7-F7-G7*D7),"") | I7: =IFERROR(IF(G7="","",H7/G7),"")
F8: =IF(B8="","",B8+C8) | G8: =IFERROR(IF(F8="","",F8/(1-D8-E8)),"rever %") | H8: =IFERROR(IF(G8="","",G8-F8-G8*D8),"") | I8: =IFERROR(IF(G8="","",H8/G8),"")
F9: =IF(B9="","",B9+C9) | G9: =IFERROR(IF(F9="","",F9/(1-D9-E9)),"rever %") | H9: =IFERROR(IF(G9="","",G9-F9-G9*D9),"") | I9: =IFERROR(IF(G9="","",H9/G9),"")
F10: =IF(B10="","",B10+C10) | G10: =IFERROR(IF(F10="","",F10/(1-D10-E10)),"rever %") | H10: =IFERROR(IF(G10="","",G10-F10-G10*D10),"") | I10: =IFERROR(IF(G10="","",H10/G10),"")
F11: =IF(B11="","",B11+C11) | G11: =IFERROR(IF(F11="","",F11/(1-D11-E11)),"rever %") | H11: =IFERROR(IF(G11="","",G11-F11-G11*D11),"") | I11: =IFERROR(IF(G11="","",H11/G11),"")
F12: =IF(B12="","",B12+C12) | G12: =IFERROR(IF(F12="","",F12/(1-D12-E12)),"rever %") | H12: =IFERROR(IF(G12="","",G12-F12-G12*D12),"") | I12: =IFERROR(IF(G12="","",H12/G12),"")
F13: =IF(B13="","",B13+C13) | G13: =IFERROR(IF(F13="","",F13/(1-D13-E13)),"rever %") | H13: =IFERROR(IF(G13="","",G13-F13-G13*D13),"") | I13: =IFERROR(IF(G13="","",H13/G13),"")
F14: =IF(B14="","",B14+C14) | G14: =IFERROR(IF(F14="","",F14/(1-D14-E14)),"rever %") | H14: =IFERROR(IF(G14="","",G14-F14-G14*D14),"") | I14: =IFERROR(IF(G14="","",H14/G14),"")
F15: =IF(B15="","",B15+C15) | G15: =IFERROR(IF(F15="","",F15/(1-D15-E15)),"rever %") | H15: =IFERROR(IF(G15="","",G15-F15-G15*D15),"") | I15: =IFERROR(IF(G15="","",H15/G15),"")
F16: =IF(B16="","",B16+C16) | G16: =IFERROR(IF(F16="","",F16/(1-D16-E16)),"rever %") | H16: =IFERROR(IF(G16="","",G16-F16-G16*D16),"") | I16: =IFERROR(IF(G16="","",H16/G16),"")
F17: =IF(B17="","",B17+C17) | G17: =IFERROR(IF(F17="","",F17/(1-D17-E17)),"rever %") | H17: =IFERROR(IF(G17="","",G17-F17-G17*D17),"") | I17: =IFERROR(IF(G17="","",H17/G17),"")
... F52: =IF(B52="","",B52+C52) | G52: =IFERROR(IF(F52="","",F52/(1-D52-E52)),"rever %") | H52: =IFERROR(IF(G52="","",G52-F52-G52*D52),"") | I52: =IFERROR(IF(G52="","",H52/G52),"")
A54: Taxas comuns: Shopee ~20% | Mercado Livre ~16% | Venda no Instagram/WhatsApp = 0%

Sheet Controle de Vendas
A1: CONTROLE DE VENDAS — anote cada venda nas colunas amarelas
A2: Data | B2: Produto | C2: Qtd | D2: Custo unit. (R$) | E2: Preço venda unit. (R$) | F2: Taxa mkt (%) | G2: Faturamento (R$) | H2: Custo total (R$) | I2: Taxa paga (R$) | J2: LUCRO (R$)
G3: =IF(C3="","",C3*E3) | H3: =IF(C3="","",C3*D3) | I3: =IF(C3="","",G3*F3) | J3: =IF(C3="","",G3-H3-I3)
G4: =IF(C4="","",C4*E4) | H4: =IF(C4="","",C4*D4) | I4: =IF(C4="","",G4*F4) | J4: =IF(C4="","",G4-H4-I4)
G5: =IF(C5="","",C5*E5) | H5: =IF(C5="","",C5*D5) | I5: =IF(C5="","",G5*F5) | J5: =IF(C5="","",G5-H5-I5)
G6: =IF(C6="","",C6*E6) | H6: =IF(C6="","",C6*D6) | I6: =IF(C6="","",G6*F6) | J6: =IF(C6="","",G6-H6-I6)
G7: =IF(C7="","",C7*E7) | H7: =IF(C7="","",C7*D7) | I7: =IF(C7="","",G7*F7) | J7: =IF(C7="","",G7-H7-I7)
G8: =IF(C8="","",C8*E8) | H8: =IF(C8="","",C8*D8) | I8: =IF(C8="","",G8*F8) | J8: =IF(C8="","",G8-H8-I8)
G9: =IF(C9="","",C9*E9) | H9: =IF(C9="","",C9*D9) | I9: =IF(C9="","",G9*F9) | J9: =IF(C9="","",G9-H9-I9)
G10: =IF(C10="","",C10*E10) | H10: =IF(C10="","",C10*D10) | I10: =IF(C10="","",G10*F10) | J10: =IF(C10="","",G10-H10-I10)
G11: =IF(C11="","",C11*E11) | H11: =IF(C11="","",C11*D11) | I11: =IF(C11="","",G11*F11) | J11: =IF(C11="","",G11-H11-I11)
G12: =IF(C12="","",C12*E12) | H12: =IF(C12="","",C12*D12) | I12: =IF(C12="","",G12*F12) | J12: =IF(C12="","",G12-H12-I12)
G13: =IF(C13="","",C13*E13) | H13: =IF(C13="","",C13*D13) | I13: =IF(C13="","",G13*F13) | J13: =IF(C13="","",G13-H13-I13)
G14: =IF(C14="","",C14*E14) | H14: =IF(C14="","",C14*D14) | I14: =IF(C14="","",G14*F14) | J14: =IF(C14="","",G14-H14-I14)
... G202: =IF(C202="","",C202*E202) | H202: =IF(C202="","",C202*D202) | I202: =IF(C202="","",G202*F202) | J202: =IF(C202="","",G202-H202-I202)
B203: TOTAL | G203: =SUM(G3:G202) | H203: =SUM(H3:H202) | I203: =SUM(I3:I202) | J203: =SUM(J3:J202)

Sheet Controle de Estoque
A1: CONTROLE DE ESTOQUE — preencha o amarelo, a planilha avisa quando repor
A2: Produto | B2: Estoque inicial | C2: Entradas (comprou) | D2: Saídas (vendeu) | E2: Estoque atual | F2: Estoque mínimo | G2: Situação
E3: =IF(A3="","",B3+C3-D3) | G3: =IF(A3="","",IF(E3<=F3,"⚠ REPOR","OK"))
E4: =IF(A4="","",B4+C4-D4) | G4: =IF(A4="","",IF(E4<=F4,"⚠ REPOR","OK"))
E5: =IF(A5="","",B5+C5-D5) | G5: =IF(A5="","",IF(E5<=F5,"⚠ REPOR","OK"))
E6: =IF(A6="","",B6+C6-D6) | G6: =IF(A6="","",IF(E6<=F6,"⚠ REPOR","OK"))
E7: =IF(A7="","",B7+C7-D7) | G7: =IF(A7="","",IF(E7<=F7,"⚠ REPOR","OK"))
E8: =IF(A8="","",B8+C8-D8) | G8: =IF(A8="","",IF(E8<=F8,"⚠ REPOR","OK"))
E9: =IF(A9="","",B9+C9-D9) | G9: =IF(A9="","",IF(E9<=F9,"⚠ REPOR","OK"))
E10: =IF(A10="","",B10+C10-D10) | G10: =IF(A10="","",IF(E10<=F10,"⚠ REPOR","OK"))
E11: =IF(A11="","",B11+C11-D11) | G11: =IF(A11="","",IF(E11<=F11,"⚠ REPOR","OK"))
E12: =IF(A12="","",B12+C12-D12) | G12: =IF(A12="","",IF(E12<=F12,"⚠ REPOR","OK"))
E13: =IF(A13="","",B13+C13-D13) | G13: =IF(A13="","",IF(E13<=F13,"⚠ REPOR","OK"))
E14: =IF(A14="","",B14+C14-D14) | G14: =IF(A14="","",IF(E14<=F14,"⚠ REPOR","OK"))
... E52: =IF(A52="","",B52+C52-D52) | G52: =IF(A52="","",IF(E52<=F52,"⚠ REPOR","OK"))

Sheet Resumo
B2: RESUMO DO SEU NEGÓCIO
B3: Atualiza sozinho conforme você lança as vendas.
B5: Faturamento total | C5: =SUM('Controle de Vendas'!G3:G202)
B6: Lucro total | C6: =SUM('Controle de Vendas'!J3:J202)
B7: Total de produtos vendidos | C7: =SUM('Controle de Vendas'!C3:C202)
B8: Número de vendas (pedidos) | C8: =COUNT('Controle de Vendas'!E3:E202)
B9: Ticket médio | C9: =IFERROR(SUM('Controle de Vendas'!G3:G202)/COUNT('Controle de Vendas'!E3:E202),0)
B10: Margem de lucro média | C10: =IFERROR(SUM('Controle de Vendas'!J3:J202)/SUM('Controle de Vendas'!G3:G202),0)
B11: Total pago em taxas | C11: =SUM('Controle de Vendas'!I3:I202)
B13: FornecedorVip — fornecedorvip.shop
